{
    "titre": "À Bord avec Christophe Colomb",
    "description" : "Traversez l’Atlantique et assistez à la découverte d’un Nouveau Monde.",
    "epoque": "Renaissance",
    "lieu": "Amérique",
    "image" : "images/Colomb.jpeg",
    "dates": {
        "choix_date_depart": true,
        "duree": "10 jours"
    },
    "prix_base": 2250,
    "prix_total": 0,
    "paiement": false,
    "nombre_personnes": 0,
    "personnes": [],
    "etape1": [
      {
        "options_disponibles": {
          "position": {
            "Caravelle La Pinta": 0,
            "Île découverte": 0,
            "Campement": 0,
            "Aucune option": 0
          },
          "activite": {
            "Navigation à voile": 60,
            "Découverte de terres": 90,
            "Coutumes indigènes": 70,
            "Aucune option": 0
          },
          "hebergement": {
            "Cabine de marin": 50,
            "Tente d’explorateur": 60,
            "Refuge de plage": 70,
            "Aucune option": 0
          },
          "restauration": {
            "Galette sèche": 10,
            "Fruits exotiques": 20,
            "Rhum colonial": 30,
            "Aucune option": 0
          },
          "transport": {
            "Voilier": 70,
            "Pirogue": 40,
            "Cheval colonial": 60,
            "Aucune option": 0
          }
        },
        "options_choisies": {},
        "personnes_supplementaires": []
      }
    ],
    "etape2": [
      {
        "options_disponibles": {
          "position": {
            "Caravelle La Pinta": 0,
            "Île découverte": 0,
            "Campement": 0,
            "Aucune option": 0
          },
          "activite": {
            "Navigation à voile": 60,
            "Découverte de terres": 90,
            "Coutumes indigènes": 70,
            "Aucune option": 0
          },
          "hebergement": {
            "Cabine de marin": 50,
            "Tente d’explorateur": 60,
            "Refuge de plage": 70,
            "Aucune option": 0
          },
          "restauration": {
            "Galette sèche": 10,
            "Fruits exotiques": 20,
            "Rhum colonial": 30,
            "Aucune option": 0
          },
          "transport": {
            "Voilier": 70,
            "Pirogue": 40,
            "Cheval colonial": 60,
            "Aucune option": 0
          }
        },
        "options_choisies": {},
        "personnes_supplementaires": []
      }
    ]
  }
  